setup.cfg
setup.py
ludibrio/__init__.py
ludibrio/_importexample.py
ludibrio/_testdouble.py
ludibrio/dependencyinjection.py
ludibrio/dummy.py
ludibrio/helpers.py
ludibrio/matcher.py
ludibrio/mock.py
ludibrio/specialarguments.py
ludibrio/spy.py
ludibrio/stub.py
ludibrio.egg-info/PKG-INFO
ludibrio.egg-info/SOURCES.txt
ludibrio.egg-info/dependency_links.txt
ludibrio.egg-info/entry_points.txt
ludibrio.egg-info/not-zip-safe
ludibrio.egg-info/top_level.txt