Metadata-Version: 1.0
Name: ludibrio
Version: 3.1.0
Summary: Platform for test doubles in Python (mocks, stubs, and dummies)
Home-page: http://nsigustavo.blogspot.com
Author: nsigustavo@gmail.com
Author-email: Gustavo Rezende
License: GPL
Keywords: mock stub fake dummy doubles mocks
Platform: UNKNOWN
